{
    "openapi": "3.0.0",
    "info": {
        "title": "My First API",
        "version": "0.1"
    },
    "paths": {
        "/": {
            "get": {
                "description": "Home page",
                "operationId": "59dd1578e0aba6cba5580a4c6eddab01",
                "responses": {
                    "default": {
                        "description": "Welcome page"
                    }
                }
            }
        }
    },
    "components": {
        "responses": {
            "200": {
                "description": "An example resource"
            }
        },
        "parameters": {
            "email": {
                "name": "email",
                "in": "query",
                "description": "이메일 주소",
                "required": true,
                "schema": {
                    "type": "string"
                }
            }
        }
    }
}